{
  "onClassTime": {
      "morning": [
        ["07:15:00", "07:50:00"],
        ["07:50:00", "08:30:00"],
        ["08:40:00", "09:20:00"],
        ["09:30:00", "09:40:00"],
        ["09:30:00", "10:10:00"],
        ["10:20:00", "11:00:00"],
        ["11:10:00", "11:50:00"]
      ],
      "afternoon": [
        ["14:10:00", "14:50:00"],
        ["15:15:00", "15:55:00"],
        ["16:05:00", "16:45:00"],
        ["16:55:00", "17:15:00"]
      ],
      "evening": [
        ["18:50:00", "20:30:00"],
        ["20:40:00", "21:00:00"],
        ["21:00:00", "21:50:00"]
      ]
    },
  "onBreakTime": {
      "morning": [
        ["08:30:00", "08:40:00"],
        ["09:20:00", "09:30:00"],
        ["10:10:00", "10:20:00"],
        ["11:00:00", "11:10:00"]
      ],
      "afternoon": [
        ["14:50:00", "15:15:00"],
        ["15:55:00", "16:05:00"],
        ["16:45:00", "16:55:00"],
        ["20:30:00", "20:40:00"]
      ]
  },
  "classArrangement": {
    "Monday": [
      "英语", "数学", "生物", "", "语文", "语文", "", "班会", "体育", "null"
    ],
    "Tuesday": [
      "语文", "化学", "", "", "", "地理", "", "", "信息", "美术/音乐"
    ],
    "Wednesday": [
      "英语", "", "", "", "地理", "生物", "物理", "语文", "自习", "null"
    ],
    "Thursday": [
      "语文", "语文", "", "体育", "数学", "数学", "心理", "自习", "历史", "跑操"
    ],
    "Friday": [
      "英语", "英语", "英语", "历史", "语文", "地理", "数学", "生物", "政治", "劳动"
    ]
  }
}